README.txt
setup.py
docs/HISTORY.txt
docs/INSTALL.txt
docs/LICENSE.GPL
docs/LICENSE.txt
simplon/__init__.py
simplon.plone.currency.egg-info/PKG-INFO
simplon.plone.currency.egg-info/SOURCES.txt
simplon.plone.currency.egg-info/dependency_links.txt
simplon.plone.currency.egg-info/namespace_packages.txt
simplon.plone.currency.egg-info/not-zip-safe
simplon.plone.currency.egg-info/requires.txt
simplon.plone.currency.egg-info/top_level.txt
simplon/plone/__init__.py
simplon/plone/currency/__init__.py
simplon/plone/currency/configure.zcml
simplon/plone/currency/currencies.py
simplon/plone/currency/currency.py
simplon/plone/currency/interfaces.py
simplon/plone/currency/manager.py
simplon/plone/currency/vocabulary.py
simplon/plone/currency/browser/__init__.py
simplon/plone/currency/browser/configure.zcml
simplon/plone/currency/browser/controlpanel.pt
simplon/plone/currency/browser/controlpanel.py
simplon/plone/currency/browser/currency.py
simplon/plone/currency/browser/interfaces.py
simplon/plone/currency/profiles/default/componentregistry.xml
simplon/plone/currency/profiles/default/controlpanel.xml
simplon/plone/currency/tests/UserInterface.txt
simplon/plone/currency/tests/base.py
simplon/plone/currency/tests/layer.py
simplon/plone/currency/tests/testCurrency.py
simplon/plone/currency/tests/testDocTest.py
simplon/plone/currency/tests/testManager.py
simplon/plone/currency/tests/testVocabulary.py
