Metadata-Version: 1.0
Name: simplon.plone.currency
Version: 1.0b2
Summary: Currency handling for Plone
Home-page: https://code.simplon.biz/svn/zope/simplon.plone.currency/trunk
Author: Wichert Akkerman
Author-email: wichert@simplon.biz
License: GPL
Platform: UNKNOWN
Classifier: Framework :: Plone
Classifier: Framework :: Zope2
Classifier: Programming Language :: Python
Classifier: Topic :: Internet :: WWW/HTTP :: Site Management
Classifier: Topic :: Software Development :: Libraries :: Python Modules
